<?xml version = '1.0' encoding = 'UTF-8'?>
<Diagram class="oracle.dbtools.crest.swingui.datatypes.DPVDataTypes" id="E57EF5CD-33E1-0976-24E2-0918843AA13B">
<createdBy>My PC</createdBy>
<modifiedBy>My PC</modifiedBy>
<createdTime>2022-06-27 15:47:51 UTC</createdTime>
<autoRoute>false</autoRoute>
<boxInbox>true</boxInbox>
<showLegend>false</showLegend>
<showLabels>true</showLabels>
<showRelAttributes>false</showRelAttributes>
<gridEnabled>false</gridEnabled>
<showGrid>false</showGrid>
<diagramColor>-1</diagramColor>
<display>false</display>
<notation>1</notation>
<objectViews>
<OView class="oracle.dbtools.crest.swingui.datatypes.TVStructuredType" oid="47E390DE-0671-C4B1-8428-0F45CBEE18F8" otype="StructuredType" vid="1192306D-AD3D-A2E4-F71C-B5CB779584D3">
<hideElementsInCurrentOnly>false</hideElementsInCurrentOnly>
<bounds x="20" y="20" width="108" height="39"/>
</OView>
<OView class="oracle.dbtools.crest.swingui.datatypes.TVStructuredType" oid="F72C39E0-D1CA-8821-2AD7-A1E95A37D3D1" otype="StructuredType" vid="0A6D9756-9012-BC91-A848-B933ECFBB4DA">
<hideElementsInCurrentOnly>false</hideElementsInCurrentOnly>
<bounds x="178" y="20" width="78" height="39"/>
</OView>
</objectViews>
</Diagram>